nhandd_test_poetry/__init__.py
nhandd_test_poetry/pretty.py
nhandd_test_poetry-1.0.0.dist-info/WHEEL
nhandd_test_poetry-1.0.0.dist-info/METADATA
nhandd_test_poetry-1.0.0.dist-info/RECORD
