Metadata-Version: 2.1
Name: nhandd-test-poetry
Version: 1.0.0
Summary: 
Author: NhanDD
Author-email: hp.duongducnhan@gmail.com
Requires-Python: >=3.10,<4.0
Classifier: Programming Language :: Python :: 3
Classifier: Programming Language :: Python :: 3.10
Classifier: Programming Language :: Python :: 3.11
Requires-Dist: pyfiglet (>=0.8.post1,<0.9)
Requires-Dist: termcolor (>=2.0.1,<3.0.0)
